README.md
setup.py
pydelighted/Delighted.py
pydelighted/__init__.py
pydelighted/useful.py
pydelighted.egg-info/PKG-INFO
pydelighted.egg-info/SOURCES.txt
pydelighted.egg-info/dependency_links.txt
pydelighted.egg-info/requires.txt
pydelighted.egg-info/top_level.txt