Metadata-Version: 2.1
Name: pydelighted
Version: 0.0.5
Summary: A Delighted connector
Home-page: https://github.com/dacker-team/pydelighted
Author: Dacker
Author-email: hello@dacker.co
License: UNKNOWN
Platform: UNKNOWN
Classifier: Programming Language :: Python :: 3
Classifier: License :: OSI Approved :: MIT License
Classifier: Operating System :: OS Independent
Requires-Python: >=3
